MANIFEST.in
RELEASE-VERSION
pavement.py
paver-minilib.zip
setup.py
version.py
electromagnet_controller/__init__.py
electromagnet_controller/Arduino/electromagnet_controller/Config.h
electromagnet_controller/Arduino/electromagnet_controller/Config.h.skeleton
electromagnet_controller/Arduino/electromagnet_controller/ElectromagnetController.cpp
electromagnet_controller/Arduino/electromagnet_controller/ElectromagnetController.h
electromagnet_controller/Arduino/electromagnet_controller/ElectromagnetController.o
electromagnet_controller/Arduino/electromagnet_controller/SConscript
electromagnet_controller/Arduino/electromagnet_controller/electromagnet_controller.ino
electromagnet_controller/firmware/electromagnet_controller.hex
wheeler.electromagnet_controller.egg-info/PKG-INFO
wheeler.electromagnet_controller.egg-info/SOURCES.txt
wheeler.electromagnet_controller.egg-info/dependency_links.txt
wheeler.electromagnet_controller.egg-info/requires.txt
wheeler.electromagnet_controller.egg-info/top_level.txt