Metadata-Version: 1.0
Name: wheeler.electromagnet-controller
Version: 0.1.post6.dev49075079
Summary: Arduino-based electromagnet controller firmware and PythonAPI.
Home-page: http://microfluidics.utoronto.ca/git/firmware___electromagnet_controller.git
Author: Ryan Fobel
Author-email: ryan@fobel.net
License: GPLv2
Platform: UNKNOWN
